kyoutubescraper/__init__.py
kyoutubescraper/_utils.py
kyoutubescraper/channel_about_data.py
kyoutubescraper/youtube_scraper.py
kyoutubescraper-0.0.2.dist-info/METADATA
kyoutubescraper-0.0.2.dist-info/WHEEL
kyoutubescraper-0.0.2.dist-info/top_level.txt
kyoutubescraper-0.0.2.dist-info/RECORD
