Metadata-Version: 2.1
Name: kyoutubescraper
Version: 0.0.2
Summary: kyoutubescraper
Home-page: https://github.com/kkristof200/py_youtube_scraper
Author: kkristof200
License: UNKNOWN
Platform: UNKNOWN
Classifier: Programming Language :: Python :: 3
Classifier: License :: OSI Approved :: MIT License
Classifier: Operating System :: OS Independent
Requires-Python: >=3.5
